LICENSE
MANIFEST.in
README
setup.py
squeeze/SoyToJsSrcCompiler.jar
squeeze/__init__.py
squeeze/closure-stylesheets.jar
squeeze/compiler.jar
squeeze/cssembed.jar
squeeze/datauri.jar
squeeze/htmlcompressor.jar
squeeze/yuicompressor-2.4.8pre.jar
squeeze/yuicompressor.jar
squeeze.egg-info/PKG-INFO
squeeze.egg-info/SOURCES.txt
squeeze.egg-info/dependency_links.txt
squeeze.egg-info/entry_points.txt
squeeze.egg-info/not-zip-safe
squeeze.egg-info/top_level.txt