Metadata-Version: 1.0
Name: squeeze
Version: 0.1.7
Summary: Bundled HTML/JS/CSS compressor and data-uri embedding tools (YUICompressor, CSSEmbed, DataURI, Google Closure Compiler, HTMLCompressor, Google Closure Stylesheets)
Home-page: http://pypi.python.org/pypi/squeeze
Author: Yesudeep Mangalapilly
Author-email: yesudeep@google.com
License: MIT License
Platform: UNKNOWN
Classifier: Development Status :: 5 - Production/Stable
Classifier: Environment :: Web Environment
Classifier: License :: OSI Approved :: MIT License
Classifier: Topic :: Internet :: WWW/HTTP :: Site Management
